<?xml version="1.0" encoding="UTF-8"?>
<data>
	<event start="Jan 01 2001 08:00:00 GMT-0600" title="George W. Bush's First Term Begins" link=""></event>
	<event start="May 25 2001 08:00:00 GMT-0600" title="Democrats gain narrow control of Senate after James Jeffords defects from the Republican Party" link=""></event>
	<event start="Sep 11 2001 08:00:00 GMT-0600" title="September 11, 2001 Terrorist Attacks on the World Trade Center and The Pentagon" link=""></event>
	<event start="Oct 07 2001 08:00:00 GMT-0600" title="Invasion of Afghanistan Operation 'Enduring Freedom'" link=""></event>
	<event start="Jun 13 2002 08:00:00 GMT-0600" title="U.S. withdraws from Anti-Ballistic Missile Treaty" link=""></event>
	<event start="Nov 07 2002 08:00:00 GMT-0600" title="Republicans retake narrow control of Senate following 2002 elections" link=""></event>
	<event start="Nov 25 2002 08:00:00 GMT-0600" title="Department of Homeland Security created" link=""></event>
	<event start="Feb 01 2003 08:00:00 GMT-0600" title="Space Shuttle Columbia disaster" link=""></event>
	<event start="Mar 20 2003 08:00:00 GMT-0600" title="Invasion of Iraq - Operation 'Iraqi Freedom' commences" link=""></event>
	<event start="May 01 2003 08:00:00 GMT-0600" title="Begin Occupation of Iraq" link=""></event>
	<event start="Jul 31 2004 08:00:00 GMT-0600" title="The 2004 Atlantic hurricane season begins" link=""></event>
	<event start="Jan 20 2005 08:00:00 GMT-0600" title="George W. Bush's Second Term Begins" link=""></event>
	<event start="Aug 29 2005 08:00:00 GMT-0600" title="Hurricane Katrina became the costliest hurricane of all time" link=""></event>
	<event start="Nov 05 2006 08:00:00 GMT-0600" title="Democrats retake control of both houses of Congress" link=""></event>
	<event start="Apr 16 2007 08:00:00 GMT-0600" title="Virginia Tech massacre" link=""></event>
	<event start="Sep 10 2007 08:00:00 GMT-0600" title="Gen. Petraeus Testifies to Congress on Iraq Surge" link=""></event>
	<event start="Apr 21 2008 19:00:00 GMT-0600" title="Guest appearance on network game show 'Deal or No Deal'" link=""></event>
	<event start="Nov 04 2008 08:00:00 GMT-0600" title="USA general election; Barack Obama defeats John McCain" link=""></event>
	<event start="Jan 20 2009 08:00:00 GMT-0600" title="Conclusion of second term" link=""></event>
</data>
